[
    {
        "Name": "Robin Milner",
        "Bibliometrics": {
            "Average Citation per Article": "95",
            "Citation count": "9,201",
            "Publication counts": "97",
            "Publication Years": "1971 - 2013",
            "Available for Download": "19",
            "Average Downloads per Article": "1,706",
            "Downloads (6 weeks)": "403",
            "Downloads (12 months)": "9,237",
            "Downloads (cumulative)": "32,421"
        },
        "Image_URL": "/do/10.1145/contrib-81332515695/full/81332515695-1588898507063.jpg",
        "Co_Authors": [],
        "Keywords": [],
        "Publications": [
            {
                "Title": "An inductive characterization of matching in binding bigraphs",
                "Details": "March 2013Formal Aspects of Computing, Volume 25, Issue 2https://doi.org/10.1007/s00165-011-0184-5",
                "DOI": "https://doi.org/10.1007/s00165-011-0184-5"
            },
            {
                "Title": "Bigraphical Categories",
                "Details": "September 2009CONCUR 2009: Proceedings of the 20th International Conference on Concurrency Theoryhttps://doi.org/10.1007/978-3-642-04081-8_3",
                "DOI": "https://doi.org/10.1007/978-3-642-04081-8_3"
            },
            {
                "Title": "Computing Tomorrow: Future Research Directions in Computer Science",
                "Details": "March 2009"
            },
            {
                "Title": "Stochastic Bigraphs",
                "Details": "October 2008Electronic Notes in Theoretical Computer Science (ENTCS), Volume 218https://doi.org/10.1016/j.entcs.2008.10.006",
                "DOI": "https://doi.org/10.1016/j.entcs.2008.10.006"
            },
            {
                "Title": "Categories, Software and Meaning",
                "Details": "June 2008Concurrency, Graphs and Modelshttps://doi.org/10.1007/978-3-540-68679-8_50",
                "DOI": "https://doi.org/10.1007/978-3-540-68679-8_50"
            },
            {
                "Title": "Bigraphs and Their Algebra",
                "Details": "April 2008Electronic Notes in Theoretical Computer Science (ENTCS), Volume 209https://doi.org/10.1016/j.entcs.2008.04.002",
                "DOI": "https://doi.org/10.1016/j.entcs.2008.04.002"
            }
        ]
    }
]